aiohttp_openapi/__init__.py
aiohttp_openapi/main.py
aiohttp_openapi/dist/favicon-16x16.png
aiohttp_openapi/dist/favicon-32x32.png
aiohttp_openapi/dist/index.html
aiohttp_openapi/dist/oauth2-redirect.html
aiohttp_openapi/dist/swagger-ui-bundle.js
aiohttp_openapi/dist/swagger-ui-bundle.js.map
aiohttp_openapi/dist/swagger-ui-standalone-preset.js
aiohttp_openapi/dist/swagger-ui-standalone-preset.js.map
aiohttp_openapi/dist/swagger-ui.css
aiohttp_openapi/dist/swagger-ui.css.map
aiohttp_openapi/dist/swagger-ui.js
aiohttp_openapi/dist/swagger-ui.js.map
aiohttp_openapi-0.1.9.dist-info/licenses/LICENSE
aiohttp_openapi-0.1.9.dist-info/METADATA
aiohttp_openapi-0.1.9.dist-info/WHEEL
aiohttp_openapi-0.1.9.dist-info/top_level.txt
aiohttp_openapi-0.1.9.dist-info/RECORD
