Metadata-Version: 2.4
Name: aiohttp-openapi
Version: 0.1.9
Summary: OpenAPI documentation builder for aiohttp server.
Home-page: https://github.com/matijabogdanovic/aiohttp-openapi
Author: Matija Bogdanovic
Author-email: matija.bogdanovic@gmail.com
Classifier: Programming Language :: Python :: 3
Classifier: License :: OSI Approved :: MIT License
Classifier: Operating System :: OS Independent
Requires-Python: >=3.6
License-File: LICENSE
Requires-Dist: aiohttp
Dynamic: author
Dynamic: author-email
Dynamic: classifier
Dynamic: description
Dynamic: description-content-type
Dynamic: home-page
Dynamic: license-file
Dynamic: requires-dist
Dynamic: requires-python
Dynamic: summary
